<?xml version="1.0" encoding="UTF-8" standalone="yes"?>
<addon id="plugin.video.rsoccer" name=" r/soccer" version="0.3" provider-name="João Sousa">
  <requires>
    <import addon="xbmc.python" version="2.1.0"/>
    <import addon="script.module.xbmcswift2" version="2.4.0"/>
  </requires>
  <extension point="xbmc.python.pluginsource" library="addon.py">
    <provides>video</provides>
  </extension>
  <extension point="xbmc.addon.metadata">
    <platform>all</platform>
    <language></language>
    <summary>Play videos from /r/soccer</summary>
    <description>Play videos from /r/soccer</description>
  </extension>
</addon>
